flyby.py
strava_flyby-0.0.6.dist-info/LICENSE
strava_flyby-0.0.6.dist-info/METADATA
strava_flyby-0.0.6.dist-info/WHEEL
strava_flyby-0.0.6.dist-info/top_level.txt
strava_flyby-0.0.6.dist-info/RECORD
