Metadata-Version: 2.1
Name: strava-flyby
Version: 0.0.6
Summary: Python client for Strava Flyby
Home-page: https://github.com/sladkovm/strava-flyby
Author: Maksym Sladkov
Author-email: sladkovm@gmail.com
License: MIT
Platform: UNKNOWN
Classifier: License :: OSI Approved :: MIT License
Classifier: Programming Language :: Python
Classifier: Programming Language :: Python :: 3.6
Classifier: Operating System :: OS Independent
Classifier: Development Status :: 3 - Alpha
Classifier: Intended Audience :: Developers
Classifier: Topic :: Scientific/Engineering
Requires-Dist: pandas
Requires-Dist: requests
Requires-Dist: loguru
